color_cli/__init__.py
color_cli/engine.py
color_cli-0.1.3.dist-info/licenses/LICENSE
color_cli-0.1.3.dist-info/licenses/NOTICE
color_cli-0.1.3.dist-info/METADATA
color_cli-0.1.3.dist-info/WHEEL
color_cli-0.1.3.dist-info/top_level.txt
color_cli-0.1.3.dist-info/RECORD
