Metadata-Version: 2.4
Name: color_cli
Version: 0.1.3
Summary: A simple coloring util for better output visibility
Home-page: https://github.com/Abdulrahman-K-S/Color-CLI
Author: Abdulrahman Khaled
Author-email: AK-Salah@outlook.com
License: Apache-2.0
Classifier: Programming Language :: Python :: 3
Requires-Python: >3.10
License-File: LICENSE
License-File: NOTICE
Requires-Dist: termcolor
Dynamic: author
Dynamic: author-email
Dynamic: classifier
Dynamic: description
Dynamic: description-content-type
Dynamic: home-page
Dynamic: license
Dynamic: license-file
Dynamic: requires-dist
Dynamic: requires-python
Dynamic: summary
